amfm_decompy/__init__.py
amfm_decompy/basic_tools.py
amfm_decompy/pYAAPT.py
amfm_decompy/pyQHM.py
amfm_decompy/sample.wav
amfm_decompy-1.0.12.2.dist-info/licenses/LICENSE
amfm_decompy-1.0.12.2.dist-info/METADATA
amfm_decompy-1.0.12.2.dist-info/WHEEL
amfm_decompy-1.0.12.2.dist-info/entry_points.txt
amfm_decompy-1.0.12.2.dist-info/top_level.txt
amfm_decompy-1.0.12.2.dist-info/RECORD
