Metadata-Version: 2.4
Name: AMFM_decompy
Version: 1.0.12.2
Summary: Package containing the tools necessary for decomposing a speech signal into its modulated components, aka AM-FM decomposition.
Author-email: "Bernardo J.B. Schmitt" <bernardo.jb.schmitt@gmail.com>
License-Expression: MIT
Project-URL: Homepage, https://github.com/bjbschmitt/AMFM_decompy/
Keywords: Python,speech,pitch,QHM,YAAPT,modulated components,AM-FM decomposition
Classifier: Programming Language :: Python :: 3
Classifier: Programming Language :: Python :: 3.5
Classifier: Programming Language :: Python :: 3.6
Classifier: Programming Language :: Python :: 3.7
Classifier: Programming Language :: Python :: 3.8
Classifier: Programming Language :: Python :: 3.9
Classifier: Programming Language :: Python :: 3.10
Classifier: Programming Language :: Python :: 3.11
Classifier: Programming Language :: Python :: 3.12
Classifier: Topic :: Scientific/Engineering
Classifier: Topic :: Scientific/Engineering :: Human Machine Interfaces
Classifier: Topic :: Scientific/Engineering :: Information Analysis
Classifier: Topic :: Software Development :: Libraries :: Python Modules
Requires-Python: >=3.5
License-File: LICENSE
Requires-Dist: numpy
Requires-Dist: scipy
Dynamic: license-file
